jn51xx_flasher/.gitignore
jn51xx_flasher/README.md
jn51xx_flasher/__init__.py
jn51xx_flasher/examples/eeprom_read.txt
jn51xx_flasher/examples/eeprom_write.txt
jn51xx_flasher/examples/flash_read.txt
jn51xx_flasher/examples/flash_read_forbidden.txt
jn51xx_flasher/examples/flash_write.txt
jn51xx_flasher/extension/FlashProgrammerExtension_JN5169.bin
jn51xx_flasher/jn51xx_emulator.py
jn51xx_flasher/jn51xx_protocol.py
jn51xx_flasher/jn51xx_sniffer.py
tweliter/__init__.py
tweliter/jn5189_flasher.py
tweliter-0.5.4.dist-info/LICENSE
tweliter-0.5.4.dist-info/METADATA
tweliter-0.5.4.dist-info/WHEEL
tweliter-0.5.4.dist-info/entry_points.txt
tweliter-0.5.4.dist-info/RECORD
