Metadata-Version: 2.3
Name: tweliter
Version: 0.5.4
Summary: Write TWELITE series firmware (beta)
Author: alnasl
Author-email: dev-alnasl@mono-wireless.com
Requires-Python: >=3.12,<4.0
Classifier: Programming Language :: Python :: 3
Classifier: Programming Language :: Python :: 3.12
Classifier: Programming Language :: Python :: 3.13
Requires-Dist: pyftdi (>=0.55.4,<0.56.0)
Requires-Dist: pyserial (>=3.5,<4.0)
Requires-Dist: tqdm (>=4.67.1,<5.0.0)
